kucoin_futures_lib/__init__.py
kucoin_futures_lib/factory.py
kucoin_futures_lib/handlers/__init__.py
kucoin_futures_lib/handlers/base.py
kucoin_futures_lib/handlers/entry.py
kucoin_futures_lib/handlers/message.py
kucoin_futures_lib/handlers/oco.py
kucoin_futures_lib/handlers/trailing.py
kucoin_futures_lib/helper.py
kucoin_futures_lib/kucoinf.py
kucoin_futures_lib/market.py
kucoin_futures_lib/trade.py
kucoin_futures_lib/user.py
kucoin_futures_lib/utils.py
kucoin_futures_lib/websocket.py
kucoin_futures_lib-0.13.0.dist-info/LICENSE
kucoin_futures_lib-0.13.0.dist-info/METADATA
kucoin_futures_lib-0.13.0.dist-info/WHEEL
kucoin_futures_lib-0.13.0.dist-info/RECORD
