Metadata-Version: 2.1
Name: kucoin-futures-lib
Version: 0.13.0
Summary: Kucoin Futures wrapper library
License: Apache-2.0
Author: Evgeny Aleshin
Requires-Python: >=3.9,<4.0
Classifier: License :: OSI Approved :: Apache Software License
Classifier: Programming Language :: Python :: 3
Classifier: Programming Language :: Python :: 3.9
Classifier: Programming Language :: Python :: 3.10
Classifier: Programming Language :: Python :: 3.11
Classifier: Programming Language :: Python :: 3.12
Requires-Dist: kucoin-futures-python (>=1.0.9,<2.0.0)
Requires-Dist: python-dotenv (>=1.0.1,<2.0.0)
